project_class1/__init__.py
project_class1/main.py
project_class1-0.1.0.dist-info/METADATA
project_class1-0.1.0.dist-info/WHEEL
project_class1-0.1.0.dist-info/RECORD
