Metadata-Version: 2.1
Name: project-class1
Version: 0.1.0
Summary: 
Author: Your Name
Author-email: you@example.com
Requires-Python: >=3.12,<4.0
Classifier: Programming Language :: Python :: 3
Classifier: Programming Language :: Python :: 3.12
Requires-Dist: pytest (>=8.1.2,<9.0.0)
Requires-Dist: requests (>=2.31.0,<3.0.0)
